idle_time/__init__.py
idle_time/__main__.py
idle_time-0.1.0.dist-info/LICENSE
idle_time-0.1.0.dist-info/WHEEL
idle_time-0.1.0.dist-info/METADATA
idle_time-0.1.0.dist-info/RECORD
