Metadata-Version: 2.1
Name: idle-time
Version: 0.1.0
Summary: Detect user idle time
Home-page: https://github.com/escaped/idle_time
License: BSD-3-Clause
Author: Alexander Frenzel
Author-email: alex@relatedworks.com
Requires-Python: >=3.7,<4.0
Classifier: Development Status :: 2 - Pre-Alpha
Classifier: Intended Audience :: Developers
Classifier: License :: OSI Approved :: BSD License
Classifier: Operating System :: OS Independent
Classifier: Programming Language :: Python
Classifier: Programming Language :: Python :: 3
Classifier: Programming Language :: Python :: 3.7
Classifier: Topic :: Software Development :: Libraries :: Python Modules
Requires-Dist: Jeepney (>=0.4.0,<0.5.0)
Requires-Dist: pywin32 (>=224.0,<225.0); sys_platform == "windows"
Project-URL: Documentation, https://github.com/escaped/idle_time
Project-URL: Repository, https://github.com/escaped/idle_time
